README.txt
setup.py
collective/__init__.py
collective.tinymceportlets.egg-info/PKG-INFO
collective.tinymceportlets.egg-info/SOURCES.txt
collective.tinymceportlets.egg-info/dependency_links.txt
collective.tinymceportlets.egg-info/entry_points.txt
collective.tinymceportlets.egg-info/namespace_packages.txt
collective.tinymceportlets.egg-info/not-zip-safe
collective.tinymceportlets.egg-info/requires.txt
collective.tinymceportlets.egg-info/top_level.txt
collective/tinymceportlets/__init__.py
collective/tinymceportlets/configure.zcml
collective/tinymceportlets/interfaces.py
collective/tinymceportlets/testing.py
collective/tinymceportlets/transform.py
collective/tinymceportlets/utils.py
collective/tinymceportlets/views.py
collective/tinymceportlets/vocabularies.py
collective/tinymceportlets/profiles/default/browserlayer.xml
collective/tinymceportlets/profiles/default/cssregistry.xml
collective/tinymceportlets/profiles/default/metadata.xml
collective/tinymceportlets/profiles/default/portlets.xml
collective/tinymceportlets/profiles/default/tinymce.xml
collective/tinymceportlets/resources/add-portlets.png
collective/tinymceportlets/resources/mceportlets.css
collective/tinymceportlets/resources/mceportlets.js
collective/tinymceportlets/templates/portlets-selection.pt
collective/tinymceportlets/tests/__init__.py
collective/tinymceportlets/tests/test_rendering.py
docs/HISTORY.txt
docs/INSTALL.txt
docs/LICENSE.GPL
docs/LICENSE.txt