Metadata-Version: 1.0
Name: collective.tinymceportlets
Version: 1.0a1
Summary: And portlets into content with tiny mce
Home-page: http://svn.plone.org/svn/collective/
Author: UNKNOWN
Author-email: UNKNOWN
License: GPL
Platform: UNKNOWN
Classifier: Framework :: Plone
Classifier: Programming Language :: Python
